{
  "groups": [
    {
      "name": "bean",
      "type": "com.cmmplb.config.beans.ConfigBean",
      "sourceType": "com.cmmplb.config.beans.ConfigBean"
    },
    {
      "name": "custom",
      "type": "com.cmmplb.config.beans.ConfigCustom",
      "sourceType": "com.cmmplb.config.beans.ConfigCustom"
    },
    {
      "name": "maven.pom",
      "type": "com.cmmplb.config.beans.Pom",
      "sourceType": "com.cmmplb.config.beans.Pom"
    },
    {
      "name": "properties",
      "type": "com.cmmplb.config.config.PropertiesConfigBean",
      "sourceType": "com.cmmplb.config.config.PropertiesConfigBean"
    }
  ],
  "properties": [
    {
      "name": "bean.name",
      "type": "java.lang.String",
      "sourceType": "com.cmmplb.config.beans.ConfigBean"
    },
    {
      "name": "bean.version",
      "type": "java.lang.String",
      "sourceType": "com.cmmplb.config.beans.ConfigBean"
    },
    {
      "name": "custom.name",
      "type": "java.lang.String",
      "sourceType": "com.cmmplb.config.beans.ConfigCustom"
    },
    {
      "name": "custom.version",
      "type": "java.lang.String",
      "sourceType": "com.cmmplb.config.beans.ConfigCustom"
    },
    {
      "name": "maven.pom.name",
      "type": "java.lang.String",
      "sourceType": "com.cmmplb.config.beans.Pom"
    },
    {
      "name": "maven.pom.version",
      "type": "java.lang.String",
      "sourceType": "com.cmmplb.config.beans.Pom"
    },
    {
      "name": "properties.name",
      "type": "java.lang.String",
      "sourceType": "com.cmmplb.config.config.PropertiesConfigBean"
    },
    {
      "name": "properties.version",
      "type": "java.lang.String",
      "sourceType": "com.cmmplb.config.config.PropertiesConfigBean"
    }
  ],
  "hints": []
}